{
  "licenseType": "CC BY",
  "creatorName": "everlaster",
  "packageName": "AutoGetDependencies",
  "standardReferenceVersionOption": "Latest",
  "scriptReferenceVersionOption": "Exact",
  "description": "v0.0.0. A comprehensive tool for scanning and downloading a package's dependencies, with many options for configuration and scene integration.",
  "credits": "VamTimbo, MacGruber",
  "instructions": "See plugin UI and Hub post.",
  "promotionalLink": "https://patreon.com/everlaster",
  "programVersion": "1.22.0.3",
  "contentList": [
    "Custom/Scripts/everlaster/AutoGetDependencies/AutoGetDependencies.cslist",
    "Custom/Scripts/everlaster/AutoGetDependencies/src"
  ],
  "dependencies": {
  },
  "customOptions": {
    "preloadMorphs": "false"
  }
}
